{
    "test": {
        "username": "test",
        "password": "$argon2id$v=19$m=65536,t=3,p=4$XqAotKAcPDGekYKar3IXvQ$g/kPB6/ndzAFzNIWaUeRR/VW1z65/Qn4qSOii/0vlXw",
        "id": "00000",
        "permission_level": "admin"
    },
    "banana": {
        "username": "banana",
        "password": "$argon2id$v=19$m=65536,t=3,p=4$seyt1cIjP8zRjRfWs8KaSw$04RT6sHQoiAE0BPaMvTtCWC+6h1O/3p5T6EVExB6LSU",
        "id": "00001",
        "permission_level": "admin"
    },
    "Toni": {
        "username": "Toni",
        "password": "$argon2id$v=19$m=65536,t=3,p=4$emwojPv1WuLBC/okkP/+Zw$o6CXIC3v5XghDg4btf+JRohezWGmaeDXtkXyUbB4/wE",
        "id": "00002",
        "permission_level": "admin"
    },
    "test2": {
        "username": "test2",
        "password": "$argon2id$v=19$m=65536,t=3,p=4$mEwnR+K98w2IuA+HOme+MA$JZlYJ/oCWta/CjUxQgHRd1E2vo12xqiGCpzLzgRcZoE",
        "id": "00003",
        "permission_level": "basic"
    },
    "Macaroni": {
        "username": "Macaroni",
        "password": "$argon2id$v=19$m=65536,t=3,p=4$xf/O0rtyMW3/Gnki5pnYxg$GNyPsUWVtVb5HYhiExiQ3aKUcdG4OpVrNvwV7xFU7Ug",
        "id": "00004",
        "permission_level": "basic"
    }
}